Metadata-Version: 2.1
Name: django-cognito-redux
Version: 1.4.5
Summary: Library for allowing the use of AWS Cognito security in Django projects
Home-page: https://github.com/patriotresearch/django-cognito-redux/
Author: Alex Plant
Author-email: alex.c.plant@gmail.com
Maintainer: Buddy Lindsey
License: UNKNOWN
Project-URL: Documentation, https://github.com/patriotresearch/django-cognito-redux/
Project-URL: Source, https://github.com/patriotresearch/django-cognito-redux/
Platform: UNKNOWN
Classifier: Development Status :: 4 - Beta
Classifier: Intended Audience :: Developers
Classifier: Natural Language :: English
Classifier: License :: OSI Approved :: MIT License
Classifier: Programming Language :: Python
Classifier: Programming Language :: Python :: 3
Classifier: Programming Language :: Python :: 3.7
Classifier: Programming Language :: Python :: 3.8
Classifier: Framework :: Django
Classifier: Framework :: Django :: 3.0
Requires-Python: >=3.7
Requires-Dist: Django (>=3.0.0)
Requires-Dist: asn1crypto (==1.2.0)
Requires-Dist: boto3 (==1.10.29)
Requires-Dist: cffi (==1.13.2)
Requires-Dist: cryptography (<4.0.0,>=3.3.1)
Requires-Dist: djangorestframework (<4.0,>=3.10.3)
Requires-Dist: idna (==2.8)
Requires-Dist: PyJWT (<2.2,>=2.1)
Requires-Dist: python-dateutil (==2.8.1)
Requires-Dist: urllib3 (==1.25.7)
